{
  "project_info": {
    "project_number": "846267411581",
    "project_id": "loginscreen-8c6e5",
    "storage_bucket": "loginscreen-8c6e5.appspot.com"
  },
  "client": [
    {
      "client_info": {
        "mobilesdk_app_id": "1:846267411581:android:a565adf9017c2f037ad514",
        "android_client_info": {
          "package_name": "com.berkay.loginscreens"
        }
      },
      "oauth_client": [
        {
          "client_id": "846267411581-bsjejkddt2md1nckgm8d30mgeb5k5np1.apps.googleusercontent.com",
          "client_type": 1,
          "android_info": {
            "package_name": "com.berkay.loginscreens",
            "certificate_hash": "9b84ef1ddd8bdc35fe3c05300dfc6e98ac2b32c8"
          }
        },
        {
          "client_id": "846267411581-vhhbil3sqbjum07t9lvnu5p0tcgruvm4.apps.googleusercontent.com",
          "client_type": 3
        }
      ],
      "api_key": [
        {
          "current_key": "AIzaSyDxLo5WcfSL_rEs_x890i0Zy4dUNOuhhJQ"
        }
      ],
      "services": {
        "appinvite_service": {
          "other_platform_oauth_client": [
            {
              "client_id": "846267411581-vhhbil3sqbjum07t9lvnu5p0tcgruvm4.apps.googleusercontent.com",
              "client_type": 3
            }
          ]
        }
      }
    }
  ],
  "configuration_version": "1"
}